balajiwork/__init__.py
balajiwork/ifc2xlsx.py
balajiwork/slowprint.py
balajiwork-1.1.6.dist-info/licenses/LICENSE
balajiwork-1.1.6.dist-info/METADATA
balajiwork-1.1.6.dist-info/WHEEL
balajiwork-1.1.6.dist-info/entry_points.txt
balajiwork-1.1.6.dist-info/top_level.txt
balajiwork-1.1.6.dist-info/RECORD
