Metadata-Version: 2.4
Name: balajiwork
Version: 1.1.6
Summary: Balaji's personal utility library
Author-email: Balaji Balagurusami <mail@balaji.work>
Requires-Python: >=3.8
License-File: LICENSE
Requires-Dist: PyPDF2
Requires-Dist: IfcOpenShell
Requires-Dist: pandas
Requires-Dist: numpy
Dynamic: license-file
